owlery_client/__init__.py
owlery_client/api_client.py
owlery_client/configuration.py
owlery_client/exceptions.py
owlery_client/model_utils.py
owlery_client/rest.py
owlery_client/schemas.py
owlery_client/api/__init__.py
owlery_client/api/dl_queries_api.py
owlery_client/api/knowledgebases_api.py
owlery_client/api/sparql_api.py
owlery_client/apis/__init__.py
owlery_client/model/__init__.py
owlery_client/model/inline_response200.py
owlery_client/model/inline_response2001.py
owlery_client/model/inline_response2002.py
owlery_client/model/inline_response2003.py
owlery_client/model/inline_response2004.py
owlery_client/model/kb_info.py
owlery_client/model/kbs_kb_equivalent_value.py
owlery_client/model/kbs_kb_subclasses_value.py
owlery_client/model/kbs_kb_superclasses_value.py
owlery_client/model/prefix_map.py
owlery_client/models/__init__.py
owlery_client-1.0.0.dist-info/METADATA
owlery_client-1.0.0.dist-info/WHEEL
owlery_client-1.0.0.dist-info/top_level.txt
owlery_client-1.0.0.dist-info/RECORD
